alu/alu.v
`timescale 1ns/100ps
 module alu(out,zero,opcode,data,accum);
 input [7:0] data,accum;
 input [2:0] opcode;
 output zero;
 output [7:0] out;
 reg [7:0] out; //
 reg zero; 
 
 parameter PASS0 = 3'b000,
           PASS1 = 3'b001,
             ADD   = 3'b010,
             AND   = 3'b011,
             XOR   = 3'b100,
             PASSD = 3'b101,
             PASS6 = 3'b110,
             PASS7 = 3'b111; 
 
// ???????????? 
 always@(opcode or data or accum)
 begin
  if(accum==8'b00000000)
	#1.2 zero=1;
  else
	#1.2 zero=0;
  case(opcode)
  PASS0:#3.5 out=accum;
  PASS1:#3.5 out=accum;
  ADD:#3.5 out=accum+data;
  AND:#3.5 out=accum&data;
  XOR:#3.5 out=accum^data;
  PASSD:#3.5 out=data;
  PASS6:#3.5 out=accum;
  PASS7:#3.5 out=accum;
  default:#3.5 out=8'bx;
endcase
 end

endmodule

alu/alu_test.v
`timescale 1 ns / 1 ns 
 
// Define the delay from stimulus to response check 
`define  DELAY  20 
module alu_test ; 
 
   wire [7:0] out ;
   reg  [7:0] data ;
   reg  [7:0] accum ;
   reg  [2:0] opcode ;
   integer    i  ; 
 
 
// Define opcodes   
parameter    PASS0 = 3'b000,
             PASS1 = 3'b001,
             ADD   = 3'b010,
             AND   = 3'b011,
             XOR   = 3'b100,
             PASSD = 3'b101,
             PASS6 = 3'b110,
             PASS7 = 3'b111; // Instantiate the ALU.  // Use explicit port mapping. 
 
  alu alu1 
 (  .out (out ), 
  .zero (zero ),
  .opcode (opcode ),
   .data (data),
   .accum (accum )  ); 
// Monitor signals 
  initial
     begin
       $display ( "<------------ INPUTS ------------> <-OUTPUTS->" ) ;
       $display ( "  TIME    OPCODE DATA IN  ACCUM IN ALU OUT  ZERO BIT" ) ;
       $display ( "--------- ------ -------- -------- -------- --------" ) ;
       $timeformat ( -9, 1, " ns", 9 ) ;
       $dumpvars(2,alu_test);
     end 
// Verify response
   task expect ;
   input [8:0] expects ;
     begin
       $display("%t %b    %b %b %b %b", $time, opcode, data, accum, out, zero ) ;
       if ( {zero,out} !== expects ) 
	begin
           $display ( "At time %t: zero is %b and should be %b, out is %b and should be %b",$time, zero, expects[8], out, expects[7:0] ) ;
           $display ( "TEST FAILED" ) ;
           $finish ;
         end
     end
   endtask 
// Apply stimulus
   initial
     begin 
 {opcode,accum,data} = {PASS0,8'h00,8'hFF}; #(`DELAY) expect({1'b1,accum     });
 {opcode,accum,data} = {PASS0,8'h55,8'hFF}; #(`DELAY) expect({1'b0,accum     });
 {opcode,accum,data} = {PASS1,8'h55,8'hFF}; #(`DELAY) expect({1'b0,accum     });
 {opcode,accum,data} = {PASS1,8'hCC,8'hFF}; #(`DELAY) expect({1'b0,accum     });
 {opcode,accum,data} = {ADD  ,8'h33,8'hAA}; #(`DELAY) expect({1'b0,accum+data});
 {opcode,accum,data} = {AND  ,8'h0F,8'h33}; #(`DELAY) expect({1'b0,accum&data});
 {opcode,accum,data} = {XOR  ,8'hF0,8'h55}; #(`DELAY) expect({1'b0,accum^data});
 {opcode,accum,data} = {PASSD,8'h00,8'hAA}; #(`DELAY) expect({1'b1,      data});
 {opcode,accum,data} = {PASSD,8'h00,8'hCC}; #(`DELAY) expect({1'b1,      data});
 {opcode,accum,data} = {PASS6,8'hFF,8'hF0}; #(`DELAY) expect({1'b0,accum     });
 {opcode,accum,data} = {PASS7,8'hCC,8'h0F}; #(`DELAY) expect({1'b0,accum     });
       $display("TEST PASSED");
       $finish;
    end 
 
endmodule

alu/dump.vcd
$date
	Thu Mar 26 20:39:25 2020
$end
$version
	ModelSim Version 10.7
$end
$timescale
	100ps
$end

$scope module alu_test $end
$var parameter 3 ! PASS0 $end
$var parameter 3 " PASS1 $end
$var parameter 3 # ADD $end
$var parameter 3 $ AND $end
$var parameter 3 % XOR $end
$var parameter 3 & PASSD $end
$var parameter 3 ' PASS6 $end
$var parameter 3 ( PASS7 $end
$var wire 1 ) out [7] $end
$var wire 1 * out [6] $end
$var wire 1 + out [5] $end
$var wire 1 , out [4] $end
$var wire 1 - out [3] $end
$var wire 1 . out [2] $end
$var wire 1 / out [1] $end
$var wire 1 0 out [0] $end
$var reg 8 1 data [7:0] $end
$var reg 8 2 accum [7:0] $end
$var reg 3 3 opcode [2:0] $end
$var integer 32 4 i $end
$var wire 1 5 zero $end

$scope task expect $end
$var reg 9 6 expects [8:0] $end
$upscope $end

$scope module alu1 $end
$var parameter 3 7 PASS0 $end
$var parameter 3 8 PASS1 $end
$var parameter 3 9 ADD $end
$var parameter 3 : AND $end
$var parameter 3 ; XOR $end
$var parameter 3 < PASSD $end
$var parameter 3 = PASS6 $end
$var parameter 3 > PASS7 $end
$var wire 1 ? data [7] $end
$var wire 1 @ data [6] $end
$var wire 1 A data [5] $end
$var wire 1 B data [4] $end
$var wire 1 C data [3] $end
$var wire 1 D data [2] $end
$var wire 1 E data [1] $end
$var wire 1 F data [0] $end
$var wire 1 G accum [7] $end
$var wire 1 H accum [6] $end
$var wire 1 I accum [5] $end
$var wire 1 J accum [4] $end
$var wire 1 K accum [3] $end
$var wire 1 L accum [2] $end
$var wire 1 M accum [1] $end
$var wire 1 N accum [0] $end
$var wire 1 O opcode [2] $end
$var wire 1 P opcode [1] $end
$var wire 1 Q opcode [0] $end
$var reg 1 R zero $end
$var reg 8 S out [7:0] $end
$upscope $end
$upscope $end
$enddefinitions $end
#0
$dumpvars
b11111111 1
b0 2
b0 3
xR
bx S
bx 6
b0 !
b1 "
b10 #
b11 $
b100 %
b101 &
b110 '
b111 (
b0 7
b1 8
b10 9
b11 :
b100 ;
b101 <
b110 =
b111 >
bx 4
x0
x/
x.
x-
x,
x+
x*
x)
x5
0N
0M
0L
0K
0J
0I
0H
0G
1F
1E
1D
1C
1B
1A
1@
1?
0Q
0P
0O
$end
#12
1R
15
#47
b0 S
00
0/
0.
0-
0,
0+
0*
0)
#200
b100000000 6
b1010101 2
1N
1L
1J
1H
#212
0R
05
#247
b1010101 S
10
1.
1,
1*
#400
b1010101 6
b1 3
1Q
#600
b11001100 2
0N
1K
0J
1G
#647
b11001100 S
00
1-
0,
1)
#800
b11001100 6
b10101010 1
b110011 2
b10 3
0Q
1P
1N
1M
0L
0K
1J
1I
0H
0G
0F
0D
0B
0@
#847
b11011101 S
10
1,
#1000
b11011101 6
b110011 1
b1111 2
b11 3
1Q
1L
1K
0J
0I
1F
0C
1B
0?
#1047
b11 S
1/
0.
0-
0,
0*
0)
#1200
b11 6
b1010101 1
b11110000 2
b100 3
0Q
0P
1O
0N
0M
0L
0K
1J
1I
1H
1G
0E
1D
0A
1@
#1247
b10100101 S
0/
1.
1+
1)
#1400
b10100101 6
b10101010 1
b0 2
b101 3
1Q
0J
0I
0H
0G
0F
1E
0D
1C
0B
1A
0@
1?
#1412
1R
15
#1447
b10101010 S
00
1/
0.
1-
#1600
b110101010 6
b11001100 1
0E
1D
0A
1@
#1647
b11001100 S
0/
1.
0+
1*
#1800
b111001100 6
b11110000 1
b11111111 2
b110 3
0Q
1P
1N
1M
1L
1K
1J
1I
1H
1G
0D
0C
1B
1A
#1812
0R
05
#1847
b11111111 S
10
1/
1,
1+
#2000
b11111111 6
b1111 1
b11001100 2
b111 3
1Q
0N
0M
0J
0I
1F
1E
1D
1C
0B
0A
0@
0?
#2047
b11001100 S
00
0/
0,
0+
#2200
b11001100 6
